Metadata-Version: 1.1
Name: WebElemental
Version: 1.4.5
Summary: An elemental force for driving web pages using Selenium and Python.
Home-page: http://github.com/IntuitiveWebSolutions/WebElemental
Author: Scott Blevins
Author-email: scottblevins@gmail.com
License: MIT
Keywords: Selenium,Testing
Platform: OS Independent
Classifier: Development Status :: 3 - Alpha
Classifier: License :: OSI Approved :: MIT License
Classifier: Operating System :: OS Independent
Classifier: Programming Language :: Python :: 2.7
Classifier: Intended Audience :: Developers
Classifier: Topic :: Software Development :: Libraries :: Python Modules
